datamachine/__init__.py
datamachine/_modular.py
datamachine-0.1.6.dist-info/LICENSE
datamachine-0.1.6.dist-info/METADATA
datamachine-0.1.6.dist-info/WHEEL
datamachine-0.1.6.dist-info/top_level.txt
datamachine-0.1.6.dist-info/RECORD
