Metadata-Version: 2.1
Name: datamachine
Version: 0.1.6
Summary: Modular Notebooks
Home-page: https://pypi.org/project/datamachine
Author: Dave Killough
Author-email: Dave Killough <dave@benevolentmachines.org>
Project-URL: Project, https://github.com/dave-killough/datamachine
Classifier: Programming Language :: Python :: 3
Classifier: License :: OSI Approved :: MIT License
Classifier: Operating System :: OS Independent
Requires-Python: >=3.7
License-File: LICENSE
